secreting/__init__.py
secreting-1.4.3.dist-info/METADATA
secreting-1.4.3.dist-info/WHEEL
secreting-1.4.3.dist-info/top_level.txt
secreting-1.4.3.dist-info/RECORD
