Metadata-Version: 2.4
Name: secreting
Version: 1.4.3
Summary: More secrets and randoms!
Dynamic: description
Dynamic: description-content-type
Dynamic: summary
